xproject/__init__.py
xproject/assets/xfrida/frida-server-16.0.0-android-arm64
xproject/assets/xfrida/frida-server-16.0.0-android-arm64.xz
xproject/assets/xwechat_ocr/demo.png
xproject/scripts/__init__.py
xproject/scripts/generate_init_py.py
xproject/scripts/renders/__init__.py
xproject/scripts/renders/render_handler_py.py
xproject/scripts/renders/render_task_py.py
xproject/scripts/renders/templates/render_handler_py/handler.py.jinja2
xproject/scripts/renders/templates/render_task_py/task.py.jinja2
xproject/xadb.py
xproject/xaliyun_oss.py
xproject/xasyncio_priority_queue.py
xproject/xbase64.py
xproject/xbytes.py
xproject/xcall.py
xproject/xclash.py
xproject/xcommand.py
xproject/xcookies.py
xproject/xdata.py
xproject/xdataclasses/__init__.py
xproject/xdataclasses/xaccount_dataclass.py
xproject/xdatetime.py
xproject/xdbs/__init__.py
xproject/xdbs/xdb.py
xproject/xdbs/xmongo_db.py
xproject/xdbs/xmysql_db.py
xproject/xdbs/xredis_db.py
xproject/xexceptions.py
xproject/xfile.py
xproject/xfrida.py
xproject/xhandler.py
xproject/xheaders.py
xproject/xhtml.py
xproject/xhttp/__init__.py
xproject/xhttp/xresponse.py
xproject/ximage.py
xproject/ximporter.py
xproject/xjavascript.py
xproject/xjson.py
xproject/xlist.py
xproject/xlogger.py
xproject/xmath.py
xproject/xmixins/__init__.py
xproject/xmixins/xdir_path_mixin.py
xproject/xmixins/xintrospection_mixin.py
xproject/xmixins/xmutable_mapping_mixin.py
xproject/xmixins/xobject_mixins/__init__.py
xproject/xmixins/xobject_mixins/xasync_context_manager_object_mixin.py
xproject/xmixins/xobject_mixins/xasync_create_instance_object_mixin.py
xproject/xmixins/xobject_mixins/xcontext_manager_object_mixin.py
xproject/xmixins/xobject_mixins/xcreate_instance_object_mixin.py
xproject/xmixins/xobject_mixins/xobject_mixin.py
xproject/xmixins/xrun_mixin.py
xproject/xnetwork.py
xproject/xnotifier.py
xproject/xpandas.py
xproject/xproject.__init__.py
xproject/xrender.py
xproject/xreverse.py
xproject/xsignal.py
xproject/xspider/__init__.py
xproject-0.2.3.dist-info/entry_points.txt
xproject-0.2.3.dist-info/LICENSE
xproject-0.2.3.dist-info/METADATA
xproject-0.2.3.dist-info/WHEEL
xproject-0.2.3.dist-info/RECORD
